setup.py
de_conf_mat/__init__.py
de_conf_mat/core.py
de_conf_mat.egg-info/PKG-INFO
de_conf_mat.egg-info/SOURCES.txt
de_conf_mat.egg-info/dependency_links.txt
de_conf_mat.egg-info/requires.txt
de_conf_mat.egg-info/top_level.txt