Metadata-Version: 1.0
Name: de-conf-mat
Version: 0.1.1
Summary: 混同行列から正解ラベル、予測ラベルのリストを取得するスクリプトです。ある事情があってこれをたくさん行う必要が出て来たため作りました。
Home-page: https://github.com/yuuuuwwww/de_conf_mat
Author: Yusuke Sakai
Author-email: y.f.sakai@gmail.com
License: UNKNOWN
Platform: UNKNOWN
